sf_veritas/__init__.py
sf_veritas/_auto_preload.py
sf_veritas/_sfconfig.c
sf_veritas/_sfconfig.cpython-310-x86_64-linux-gnu.so
sf_veritas/_sfcrashhandler.c
sf_veritas/_sfcrashhandler.cpython-310-x86_64-linux-gnu.so
sf_veritas/_sffastlog.c
sf_veritas/_sffastlog.cpython-310-x86_64-linux-gnu.so
sf_veritas/_sffastnet.c
sf_veritas/_sffastnet.cpython-310-x86_64-linux-gnu.so
sf_veritas/_sffastnetworkrequest.c
sf_veritas/_sffastnetworkrequest.cpython-310-x86_64-linux-gnu.so
sf_veritas/_sffuncspan.c
sf_veritas/_sffuncspan.cpython-310-x86_64-linux-gnu.so
sf_veritas/_sffuncspan_config.c
sf_veritas/_sffuncspan_config.cpython-310-x86_64-linux-gnu.so
sf_veritas/_sfheadercheck.c
sf_veritas/_sfheadercheck.cpython-310-x86_64-linux-gnu.so
sf_veritas/_sfnetworkhop.c
sf_veritas/_sfnetworkhop.cpython-310-x86_64-linux-gnu.so
sf_veritas/_sfservice.c
sf_veritas/_sfservice.cpython-310-x86_64-linux-gnu.so
sf_veritas/_sfteepreload.c
sf_veritas/app_config.py
sf_veritas/cli.py
sf_veritas/constants.py
sf_veritas/custom_excepthook.py
sf_veritas/custom_log_handler.py
sf_veritas/custom_output_wrapper.py
sf_veritas/custom_print.py
sf_veritas/django_app.py
sf_veritas/env_vars.py
sf_veritas/exception_handling_middleware.py
sf_veritas/exception_metaclass.py
sf_veritas/fast_frame_info.py
sf_veritas/fast_network_hop.py
sf_veritas/frame_tools.py
sf_veritas/funcspan_config_loader.py
sf_veritas/function_span_profiler.py
sf_veritas/get_preload_path.py
sf_veritas/import_hook.py
sf_veritas/interceptors.py
sf_veritas/libsfnettee.so
sf_veritas/local_env_detect.py
sf_veritas/package_metadata.py
sf_veritas/print_override.py
sf_veritas/regular_data_transmitter.py
sf_veritas/request_interceptor.py
sf_veritas/request_utils.py
sf_veritas/segfault_handler.py
sf_veritas/server_status.py
sf_veritas/shutdown_flag.py
sf_veritas/subprocess_startup.py
sf_veritas/test_cli.py
sf_veritas/thread_local.py
sf_veritas/timeutil.py
sf_veritas/transmit_exception_to_sailfish.py
sf_veritas-0.11.8.dist-info/METADATA
sf_veritas-0.11.8.dist-info/WHEEL
sf_veritas-0.11.8.dist-info/entry_points.txt
sf_veritas-0.11.8.dist-info/top_level.txt
sf_veritas-0.11.8.dist-info/RECORD
