Metadata-Version: 2.1
Name: sf-veritas
Version: 0.11.8
Summary: Middleware for Django, Flask, and FastAPI to intercept requests, logs, and exceptions.
Author-email: Eric Meadows <em@sailfishqa.com>
License: Proprietary
Requires-Python: >=3.9
Requires-Dist: deepmerge>=1.1.1
Requires-Dist: fire>=0.7.0
Requires-Dist: ntplib>=0.4.0
Requires-Dist: pydantic>=2.9.2
Requires-Dist: tldextract>=5.1.2
Requires-Dist: python-dateutil>=2.9.0.post0
Requires-Dist: orjson>=3.11.3
Requires-Dist: pyyaml>=6.0
Requires-Dist: tomli>=2.0.0; python_version < "3.11"
Requires-Dist: wrapt>=1.17.0
Provides-Extra: django
Requires-Dist: django; extra == "django"
Provides-Extra: flask
Requires-Dist: flask; extra == "flask"
Provides-Extra: fastapi
Requires-Dist: fastapi; extra == "fastapi"
Provides-Extra: requests
Requires-Dist: requests>=2.25.1; extra == "requests"
Provides-Extra: httpcore
Requires-Dist: httpcore[asyncio,http2,socks,trio]>=1.0.9; extra == "httpcore"
Provides-Extra: httpx
Requires-Dist: httpx[http2]>=0.28.1; extra == "httpx"
Provides-Extra: niquests
Requires-Dist: niquests>=3.15.2; extra == "niquests"
Provides-Extra: pycurl
Requires-Dist: pycurl>=7.45.7; extra == "pycurl"
Provides-Extra: all-network
Requires-Dist: requests>=2.25.1; extra == "all-network"
Requires-Dist: httpcore[asyncio,http2,socks,trio]>=1.0.9; extra == "all-network"
Requires-Dist: httpx[http2]>=0.28.1; extra == "all-network"
Requires-Dist: niquests>=3.15.2; extra == "all-network"
Requires-Dist: pycurl>=7.45.7; extra == "all-network"
